{
"page" : "3358",
"total" : "15515",
"records" : "310295",
"rows":[
{"id":"1","cell":["1","2018","Davis","MARIYA S","SHAYESHNIKOVA","ULTRASOUND TCHNO SR","78625.00","76415.00","621.00","1589.00"]},
{"id":"2","cell":["2","2018","San Diego","JASON KIRK","HOOPER","PHYS THER 2 NEX","78625.00","77800.00","75.00","750.00"]},
{"id":"3","cell":["3","2018","San Francisco","*****","*****","RESID PHYS II-VIII/NON REP","78623.00","58497.00","0.00","20126.00"]},
{"id":"4","cell":["4","2018","Irvine","MARC DAVID","PALAZZO","MGT SVC OFCR 3 SUPV","78622.00","78622.00","0.00","0.00"]},
{"id":"5","cell":["5","2018","San Diego","PATRICIA","MORAES","CLIN NURSE 2","78620.00","78620.00","0.00","0.00"]},
{"id":"6","cell":["6","2018","San Diego","JESSE CHARLES","SIMMERS","ELECTRN","78620.00","78589.00","0.00","31.00"]},
{"id":"7","cell":["7","2018","Berkeley","ALEXANDRA","MARAVILLA","BUS SYS ANL 3","78620.00","78120.00","0.00","500.00"]},
{"id":"8","cell":["8","2018","Davis","MADELINE","NIEVES-CINTRON","ASST PROF IN RES-HCOMP","78619.00","78617.00","0.00","2.00"]},
{"id":"9","cell":["9","2018","San Diego","JOSEPH JAMES IMA","GUM","SRA 3","78619.00","60621.00","0.00","17998.00"]},
{"id":"10","cell":["10","2018","Los Angeles","LEON","VICENTE","ADMIN SPEC","78618.00","60906.00","17412.00","300.00"]},
{"id":"11","cell":["11","2018","San Diego","*****","*****","OTH POST-MD TRAIN 2-8/NON REP","78618.00","70818.00","0.00","7800.00"]},
{"id":"12","cell":["12","2018","Los Angeles","DING","WANG","ASST PROJ SCIENTIST-FY","78617.00","78617.00","0.00","0.00"]},
{"id":"13","cell":["13","2018","Los Angeles","CHUN MING DOMINIC","NG","ASST PROJ SCIENTIST-FY","78617.00","78617.00","0.00","0.00"]},
{"id":"14","cell":["14","2018","San Francisco","KAI A","LAMMINEN","ADMIN OFCR 3","78615.00","77615.00","0.00","1000.00"]},
{"id":"15","cell":["15","2018","San Diego","LAUREN EGAN","BOGART","MARKETING SPEC 3","78613.00","77613.00","0.00","1000.00"]},
{"id":"16","cell":["16","2018","Davis","MARY T","ROBERTS","SRA 3","78612.00","78612.00","0.00","0.00"]},
{"id":"17","cell":["17","2018","Los Angeles","RENITA","JOSEPH","CLIN NURSE 2","78611.00","68569.00","291.00","9751.00"]},
{"id":"18","cell":["18","2018","San Diego","CATHERINE A.","RIDGWAY","PHYSCN AST SR","78611.00","72564.00","458.00","5589.00"]},
{"id":"19","cell":["19","2018","Davis","DANIEL C","COOPER","ELECTRN","78608.00","77941.00","167.00","500.00"]},
{"id":"20","cell":["20","2018","San Francisco","AMY","LI","TRAINER 3","78607.00","78607.00","0.00","0.00"]}]
}
