{
"page" : "3578",
"total" : "15515",
"records" : "310295",
"rows":[
{"id":"1","cell":["1","2018","Riverside","XOCHITL","CHAVEZ","ASST PROF-AY","74683.00","74683.00","0.00","0.00"]},
{"id":"2","cell":["2","2018","Los Angeles","MENKHU","TOLL","CLIN NURSE 2","74682.00","71764.00","42.00","2876.00"]},
{"id":"3","cell":["3","2018","Los Angeles","*****","*****","RESID PHYS II-VIII/NON REP","74682.00","59093.00","0.00","8687.00"]},
{"id":"4","cell":["4","2018","San Francisco","ERIN ELIZABETH","WINGO","RSCH DATA ANL 3","74681.00","73681.00","0.00","1000.00"]},
{"id":"5","cell":["5","2018","Davis","RYAN","DUNCAN","MACHINIST","74678.00","74678.00","0.00","0.00"]},
{"id":"6","cell":["6","2018","Davis","MICHAEL S","FREEMAN","SHEETMETAL MECH","74678.00","74678.00","0.00","0.00"]},
{"id":"7","cell":["7","2018","Los Angeles","JOSIE","TOVAR","VOC NURSE SR","74677.00","72736.00","1390.00","551.00"]},
{"id":"8","cell":["8","2018","Los Angeles","ELTON","VAN DER WALT","ADMIN ANL SR","74677.00","73677.00","0.00","1000.00"]},
{"id":"9","cell":["9","2018","San Francisco","SANDY LINH TU","DIEP","CARE SUPV 1","74676.00","72688.00","0.00","1988.00"]},
{"id":"10","cell":["10","2018","Riverside","JORGE","SANCHEZ","COMM SPEC 3","74675.00","74675.00","0.00","0.00"]},
{"id":"11","cell":["11","2018","Berkeley","DIANE","TAKESHITA","FUNDRAISER 3","74674.00","74674.00","0.00","0.00"]},
{"id":"12","cell":["12","2018","Berkeley","VLADIMIR","FORONDA","FUNDRAISER 3","74674.00","74674.00","0.00","0.00"]},
{"id":"13","cell":["13","2018","San Francisco","VISHALLI","LOOMBA","AMBUL CARE ADMSTN CRD 2","74673.00","67352.00","5007.00","2314.00"]},
{"id":"14","cell":["14","2018","Los Angeles","RAMEZ","SOLIMAN","ADMIN ANL","74673.00","69778.00","2294.00","2601.00"]},
{"id":"15","cell":["15","2018","Davis","MAXWELL M","MATSUMOTO","APPLICATIONS PROGR 3","74673.00","74673.00","0.00","0.00"]},
{"id":"16","cell":["16","2018","Berkeley","BRIAN","PASLEY","ASST RES-FY","74673.00","74673.00","0.00","0.00"]},
{"id":"17","cell":["17","2018","Los Angeles","SABAH","AKMAL","CLIN SOCIAL WORKER 3","74669.00","74669.00","0.00","0.00"]},
{"id":"18","cell":["18","2018","Santa Cruz","STEPHANIE L","BAILEY","LECT-AY","74669.00","65574.00","0.00","9095.00"]},
{"id":"19","cell":["19","2018","San Francisco","CHELSEA S.","BAHNEY","ASST ADJ PROF-FY","74668.00","66526.00","0.00","8142.00"]},
{"id":"20","cell":["20","2018","San Francisco","*****","*****","RESID PHYS II-VIII/NON REP","74668.00","59093.00","0.00","15575.00"]}]
}
