{
"page" : "2037",
"total" : "15515",
"records" : "310295",
"rows":[
{"id":"1","cell":["1","2018","Los Angeles","REMEDIOS","VILLAPA","CLIN NURSE 2","111396.00","93680.00","2735.00","14981.00"]},
{"id":"2","cell":["2","2018","Los Angeles","KENYA","COVINGTON","LECT SOE-AY","111396.00","102768.00","0.00","8628.00"]},
{"id":"3","cell":["3","2018","San Diego","ERIC RICHARD","SCOTT","SYS INTEGRATION ENGR 4","111395.00","110395.00","0.00","1000.00"]},
{"id":"4","cell":["4","2018","Irvine","PATRICK JOHN","CAYABYAB","CLIN NURSE 2","111391.00","89608.00","14222.00","7561.00"]},
{"id":"5","cell":["5","2018","Davis","DREW","HALFMANN","ASSOC PROF-AY","111390.00","111390.00","0.00","0.00"]},
{"id":"6","cell":["6","2018","San Francisco","KYLE BURKE","JONES","HS ASST CLIN PROF-HCOMP","111389.00","97759.00","0.00","13630.00"]},
{"id":"7","cell":["7","2018","Davis","BENJAMIN E","WORMELI","CLIN APPLICATIONS PROFL 4","111389.00","110514.00","0.00","875.00"]},
{"id":"8","cell":["8","2018","San Diego","MATHEW C","ADAMS","RECR MGR 2","111389.00","111389.00","0.00","0.00"]},
{"id":"9","cell":["9","2018","Riverside","ANDREAS","WESTPHAL","ASSOC SPECIALIST COOP EXT","111383.00","111383.00","0.00","0.00"]},
{"id":"10","cell":["10","2018","San Francisco","ONNA","LEE","NTRTN AND DIETARY SUPV 1","111378.00","101158.00","0.00","10220.00"]},
{"id":"11","cell":["11","2018","Berkeley","JOHN","SHIOSHITA","SYS ADM 3","111378.00","111378.00","0.00","0.00"]},
{"id":"12","cell":["12","2018","Los Angeles","JAYNE","RUNGPIPAT","CLIN NURSE 2","111377.00","101459.00","3774.00","6144.00"]},
{"id":"13","cell":["13","2018","UCOP","VIRGINIA","DELANEY","RSCH GNT PRG OFCR 4","111377.00","111377.00","0.00","0.00"]},
{"id":"14","cell":["14","2018","San Francisco","CHRIS E.","SIMEONE","GEOGRAPHIC INFO SYS PROGR 4","111376.00","110376.00","0.00","1000.00"]},
{"id":"15","cell":["15","2018","San Francisco","*****","*****","POSTDOC-EMPLOYEE","111376.00","41199.00","0.00","70177.00"]},
{"id":"16","cell":["16","2018","Berkeley","RICHARD","PRATT","APPLICATIONS PROGR 4","111375.00","111375.00","0.00","0.00"]},
{"id":"17","cell":["17","2018","Davis","BRITTANY N","DUGGER","ASST PROF IN RES-HCOMP","111375.00","91538.00","0.00","19837.00"]},
{"id":"18","cell":["18","2018","Los Angeles","NASIM","ANNABI","ASST PROF-AY-B/E/E","111375.00","56249.00","0.00","55126.00"]},
{"id":"19","cell":["19","2018","Los Angeles","KATHLEEN","BUDAS","DIR","111375.00","111375.00","0.00","0.00"]},
{"id":"20","cell":["20","2018","Davis","OANH L","MEYER","ASST ADJ PROF-HCOMP","111375.00","91213.00","0.00","20162.00"]}]
}
