{
"page" : "2885",
"total" : "15515",
"records" : "310295",
"rows":[
{"id":"1","cell":["1","2018","San Diego","PRABHLEEN","SINGH","ASSOC PROF IN RES-HCOMP","88626.00","88234.00","0.00","392.00"]},
{"id":"2","cell":["2","2018","San Francisco","LEILA M","SHARIFI","HR GENERALIST 3","88625.00","87625.00","0.00","1000.00"]},
{"id":"3","cell":["3","2018","Davis","KATE","TWEDDALE","ADMIN SUPV 2","88618.00","88618.00","0.00","0.00"]},
{"id":"4","cell":["4","2018","San Diego","MAUREEN C.","FEELEY","LECT SOE-AY","88618.00","88618.00","0.00","0.00"]},
{"id":"5","cell":["5","2018","Irvine","JOE WENDELL","HARVEY","DIR","88617.00","88617.00","0.00","0.00"]},
{"id":"6","cell":["6","2018","Los Angeles","JANET","KIERNAN","MGT SVC OFCR 2","88617.00","88617.00","0.00","0.00"]},
{"id":"7","cell":["7","2018","San Diego","ABIGAIL L.","ANDREWS","ASST PROF-AY","88617.00","88417.00","0.00","200.00"]},
{"id":"8","cell":["8","2018","San Diego","ERIK JAMES","MIRANDA","RESP CARE PRACT TCHN","88614.00","75239.00","9262.00","4113.00"]},
{"id":"9","cell":["9","2018","San Diego","REGALADO F","WHITNEY","CTRL STERILE SUPV 1","88613.00","83829.00","3766.00","1018.00"]},
{"id":"10","cell":["10","2018","Davis","LESLIE A","NEMETH","ADMIN SUPV 2","88612.00","88612.00","0.00","0.00"]},
{"id":"11","cell":["11","2018","Santa Barbara","SHU CHUAN","CHEN","LECT-AY-CONTINUING","88611.00","80259.00","0.00","8352.00"]},
{"id":"12","cell":["12","2018","Irvine","MARIA","MEDINA","ADMIN ANL PRN SUPV","88610.00","88610.00","0.00","0.00"]},
{"id":"13","cell":["13","2018","Santa Barbara","JACK","RIVAS","STDT ACAD ADVISOR 4","88610.00","87410.00","0.00","1200.00"]},
{"id":"14","cell":["14","2018","San Diego","PHOEBE CLAIRE","DE VERA","CLIN LAB SCI SPEC","88605.00","84289.00","104.00","4212.00"]},
{"id":"15","cell":["15","2018","San Francisco","*****","*****","HS ASST CLIN PROF-HCOMP","88604.00","63054.00","0.00","25550.00"]},
{"id":"16","cell":["16","2018","San Diego","DONNA K","SILVERSTEIN","ADJ PROF-HCOMP","88604.00","88604.00","0.00","0.00"]},
{"id":"17","cell":["17","2018","Los Angeles","JENNIFER","MEMPIN","EHS SPEC 3","88602.00","84729.00","0.00","3873.00"]},
{"id":"18","cell":["18","2018","Berkeley","RAYMOND","FONG","RSCH ADM 4","88602.00","87602.00","0.00","1000.00"]},
{"id":"19","cell":["19","2018","Merced","JEFFEREY","PEDRO","SYS ADM 4","88600.00","88100.00","0.00","500.00"]},
{"id":"20","cell":["20","2018","Berkeley","MONA","NAGAI","REGISTRAR COLL MGR 1","88600.00","88100.00","0.00","500.00"]}]
}
