{
"page" : "4719",
"total" : "15515",
"records" : "310295",
"rows":[
{"id":"1","cell":["1","2018","Berkeley","ANDREA","MEJIA VALENCIA","STDT SVC ADVISOR 3","60108.00","57043.00","0.00","3065.00"]},
{"id":"2","cell":["2","2018","Irvine","MALCOLM J","BOURNE","STDT AFFAIRS OFCR 3 EX","60106.00","60106.00","0.00","0.00"]},
{"id":"3","cell":["3","2018","UCOP","KASEY","UDINK","BENEFITS ANL 2","60106.00","60106.00","0.00","0.00"]},
{"id":"4","cell":["4","2018","UCOP","ADRIANA","MOLINA","BENEFITS ANL 2","60106.00","60106.00","0.00","0.00"]},
{"id":"5","cell":["5","2018","UCOP","ANN","RANGEL","BENEFITS ANL 2","60106.00","60106.00","0.00","0.00"]},
{"id":"6","cell":["6","2018","Los Angeles","MIRIAM","LOPEZ","ADMIN ANL","60105.00","58682.00","938.00","485.00"]},
{"id":"7","cell":["7","2018","Davis","ROSA","BECKWITH","PAT BILLER 3","60105.00","58603.00","1502.00","0.00"]},
{"id":"8","cell":["8","2018","San Diego","SUE ANKHELYI","BRICK","BLANK AST 3","60105.00","59105.00","0.00","1000.00"]},
{"id":"9","cell":["9","2018","San Francisco","ERICA Y.","WU","PRACTICE CRD 3","60104.00","53270.00","2855.00","3979.00"]},
{"id":"10","cell":["10","2018","San Diego","QUETZALLI","SERRANO-CAMPOS","EMPLOYMENT REPR 2","60104.00","58666.00","438.00","1000.00"]},
{"id":"11","cell":["11","2018","San Francisco","BLAIR KENDALL,MPH","BARRETT","POPULATION HEALTH MGR 1","60103.00","50793.00","0.00","9310.00"]},
{"id":"12","cell":["12","2018","Los Angeles","VERONICA","GARCIA","HOSP BLANK AST 3","60103.00","59949.00","110.00","44.00"]},
{"id":"13","cell":["13","2018","San Diego","DANIEL G","HAZLETT","HR GENERALIST 2","60102.00","55062.00","40.00","5000.00"]},
{"id":"14","cell":["14","2018","Los Angeles","SANDRA","MOLINA","ADMIN ANL","60101.00","59556.00","0.00","545.00"]},
{"id":"15","cell":["15","2018","Davis","DIANA","DIAZ","HEALTH TCHN 3","60101.00","47112.00","11914.00","1075.00"]},
{"id":"16","cell":["16","2018","San Diego","CRYSTAL REYNA","GONZALEZ","HOSP BLANK AST 3","60101.00","50299.00","5634.00","4168.00"]},
{"id":"17","cell":["17","2018","Berkeley","VANESSA","BOEHM","POSTDOC-EMPLOYEE","60100.00","60100.00","0.00","0.00"]},
{"id":"18","cell":["18","2018","San Francisco","*****","*****","RESID PHYS II-VIII/NON REP","60100.00","58900.00","0.00","1200.00"]},
{"id":"19","cell":["19","2018","Irvine","DANIEL A","PYENSON","MGT SVC OFCR 1","60100.00","60100.00","0.00","0.00"]},
{"id":"20","cell":["20","2018","Santa Barbara","FRANCES","FOUCH","STDT SVC ADVISOR 3","60100.00","59600.00","0.00","500.00"]}]
}
