{
"page" : "671",
"total" : "15515",
"records" : "310295",
"rows":[
{"id":"1","cell":["1","2018","San Francisco","CHUNHUI","GAN","CLIN NURSE 2","183984.00","158963.00","2934.00","22087.00"]},
{"id":"2","cell":["2","2018","San Francisco","CHARLES EDWARD","GREEN","INFO SYS MGR 1","183972.00","163573.00","0.00","20399.00"]},
{"id":"3","cell":["3","2018","Irvine","LUIS","MOTA-BRAVO","ACADEMIC COORD III-FY","183971.00","183971.00","0.00","0.00"]},
{"id":"4","cell":["4","2018","San Francisco","DAVID JOHN","SPENSER","SYS INTEGRATION ENGR 4","183970.00","166445.00","0.00","17525.00"]},
{"id":"5","cell":["5","2018","San Francisco","WILLIAM J","FLANAGAN","CLIN NURSE 2","183968.00","153450.00","655.00","29863.00"]},
{"id":"6","cell":["6","2018","San Francisco","JENNIFER J.","HAGERTY","CLIN NURSE 2","183932.00","177634.00","3556.00","2742.00"]},
{"id":"7","cell":["7","2018","Los Angeles","SHERONA","BAU","NURSE PRACT 3","183927.00","169145.00","9886.00","4896.00"]},
{"id":"8","cell":["8","2018","Los Angeles","SHARON","FARB","DIR ASC","183926.00","179926.00","0.00","4000.00"]},
{"id":"9","cell":["9","2018","San Diego","ADAM M","BURGOYNE","HS ASST CLIN PROF-HCOMP","183924.00","118312.00","0.00","65612.00"]},
{"id":"10","cell":["10","2018","Davis","DOUGLAS S","GROSS","SR LECT SOE-HCOMP","183916.00","183916.00","0.00","0.00"]},
{"id":"11","cell":["11","2018","Berkeley","HARTMUT","HAEFFNER","ASSOC PROF-AY","183911.00","137767.00","0.00","46144.00"]},
{"id":"12","cell":["12","2018","San Francisco","SARAH O","GLASS","FINANCIAL ANL MGR 2","183909.00","183909.00","0.00","0.00"]},
{"id":"13","cell":["13","2018","Davis","HARRY","WONG","PHARMACY SUPV 2","183909.00","179305.00","0.00","4604.00"]},
{"id":"14","cell":["14","2018","San Diego","FONNA","FORMAN","ASSOC PROF-AY","183908.00","126854.00","0.00","57054.00"]},
{"id":"15","cell":["15","2018","Los Angeles","NATALYA","NELSON","MGR","183896.00","162405.00","0.00","21491.00"]},
{"id":"16","cell":["16","2018","San Francisco","MABEL ANN","CHAN","HS ASSOC CLIN PROF-HCOMP","183894.00","120489.00","0.00","63405.00"]},
{"id":"17","cell":["17","2018","Santa Cruz","ANDREA MARIE","WILLER","ADMIN MGR 1","183891.00","36880.00","0.00","147011.00"]},
{"id":"18","cell":["18","2018","Los Angeles","STEPHEN","YU","DEAN AST","183881.00","183881.00","0.00","0.00"]},
{"id":"19","cell":["19","2018","Irvine","MARK E","MAPSTONE","HS CLIN PROF-HCOMP","183875.00","124844.00","0.00","59031.00"]},
{"id":"20","cell":["20","2018","Davis","KIM L","SCHAFER","NURSE PRACT 2","183850.00","176510.00","7340.00","0.00"]}]
}
