{
"page" : "7276",
"total" : "15515",
"records" : "310295",
"rows":[
{"id":"1","cell":["1","2018","Berkeley","CAROLYN","WINTER","STDT SVC ADVISOR 3","34385.00","33631.00","0.00","754.00"]},
{"id":"2","cell":["2","2018","Los Angeles","*****","*****","GSR-PARTIAL FEE REM","34382.00","34382.00","0.00","0.00"]},
{"id":"3","cell":["3","2018","Davis","SHAHIDEH","NOURI","ASST PROJ SCIENTIST-FY","34382.00","28885.00","0.00","5497.00"]},
{"id":"4","cell":["4","2018","San Francisco","JONATHON J","WOO","SRA 1","34380.00","29302.00","55.00","5023.00"]},
{"id":"5","cell":["5","2018","Berkeley","HECTOR","ALVAREZ","CUSTODIAN SR","34378.00","32538.00","1734.00","106.00"]},
{"id":"6","cell":["6","2018","Los Angeles","SHERYL","YEAGER","PAT COMM REPR","34378.00","33987.00","391.00","0.00"]},
{"id":"7","cell":["7","2018","San Diego","DIANA P","HERNANDEZ","STDT SVC ADVISOR 2","34377.00","32304.00","0.00","2073.00"]},
{"id":"8","cell":["8","2018","Berkeley","*****","*****","TEACHG ASST-GSHIP","34375.00","34275.00","0.00","100.00"]},
{"id":"9","cell":["9","2018","Berkeley","*****","*****","TEACHG ASST-GSHIP","34375.00","34275.00","0.00","100.00"]},
{"id":"10","cell":["10","2018","Berkeley","ADAM","BENKATO","VIS ASST PROF","34375.00","34375.00","0.00","0.00"]},
{"id":"11","cell":["11","2018","San Francisco","ANDREAS","PINTERITS","ORGANIZATIONAL CNSLT 4","34375.00","34375.00","0.00","0.00"]},
{"id":"12","cell":["12","2018","San Francisco","RAMONA","BATRA","PROJECT POLICY ANL 4","34375.00","34375.00","0.00","0.00"]},
{"id":"13","cell":["13","2018","San Francisco","KATHRYN D.","WOON","ADMIN OFCR 2","34374.00","34160.00","214.00","0.00"]},
{"id":"14","cell":["14","2018","Los Angeles","WHITNEY","ADAMS","NURSE PD","34374.00","31193.00","288.00","2893.00"]},
{"id":"15","cell":["15","2018","Santa Cruz","*****","*****","GSR-PARTIAL FEE REM","34374.00","34374.00","0.00","0.00"]},
{"id":"16","cell":["16","2018","Los Angeles","ANURADHA","KANUNGO","HS CLIN INSTR-HCOMP","34373.00","25725.00","0.00","8648.00"]},
{"id":"17","cell":["17","2018","San Diego","MARC JANN CAYABA","GONZALES","EMERGENCY TRAUMA TCHN","34373.00","29701.00","709.00","3963.00"]},
{"id":"18","cell":["18","2018","Berkeley","YI YI MON","KYO","POSTDOC-EMPLOYEE","34373.00","34373.00","0.00","0.00"]},
{"id":"19","cell":["19","2018","Santa Barbara","*****","*****","GSR-NO REM","34369.00","33798.00","0.00","571.00"]},
{"id":"20","cell":["20","2018","Davis","MAYRA Y","DIAZ","CMTY EDUC SPEC 1","34369.00","33869.00","0.00","500.00"]}]
}
