{
"page" : "7223",
"total" : "15515",
"records" : "310295",
"rows":[
{"id":"1","cell":["1","2018","Los Angeles","JENNIE","KUSNADI","NUC MED TCHNO SR","34975.00","32055.00","259.00","2661.00"]},
{"id":"2","cell":["2","2018","Los Angeles","JENNA LISA","GUYNN","CLIN NURSE 2","34975.00","24895.00","2537.00","7543.00"]},
{"id":"3","cell":["3","2018","San Francisco","ELODIE J","STEFFEN","ADMIN OFCR 3","34974.00","32532.00","0.00","2442.00"]},
{"id":"4","cell":["4","2018","Los Angeles","SANDRA","RODRIGUEZ","ADMIN ANL","34974.00","34512.00","462.00","0.00"]},
{"id":"5","cell":["5","2018","San Francisco","JOHN D B","FEATHERSTONE","DEAN","34972.00","26926.00","0.00","8046.00"]},
{"id":"6","cell":["6","2018","Irvine","SENEM BAHAR","CEVIK","LECT-AY","34972.00","34972.00","0.00","0.00"]},
{"id":"7","cell":["7","2018","Irvine","RAFFAELE","MARI","LECT-AY-1/9","34971.00","23247.00","0.00","11724.00"]},
{"id":"8","cell":["8","2018","Santa Cruz","AMANDA J","ALONZO","MED AST 2","34971.00","34955.00","16.00","0.00"]},
{"id":"9","cell":["9","2018","Santa Barbara","*****","*****","GSR-TUIT & FEE REM","34971.00","34871.00","0.00","100.00"]},
{"id":"10","cell":["10","2018","Berkeley","ROBIN","DAVIDSON","STDT SVC ADVISOR 3","34971.00","34471.00","0.00","500.00"]},
{"id":"11","cell":["11","2018","San Francisco","ANTHONY J","BAKER","ADJ PROF-FY","34969.00","34669.00","0.00","300.00"]},
{"id":"12","cell":["12","2018","Irvine","S ELAINE","TULVING","BLANK AST 2","34969.00","34958.00","0.00","11.00"]},
{"id":"13","cell":["13","2018","San Diego","VINCENT E","CULLIVER","TCHN","34969.00","31915.00","3054.00","0.00"]},
{"id":"14","cell":["14","2018","Irvine","AMY DOREEN","GAONA","BLANK AST 1","34967.00","34813.00","115.00","39.00"]},
{"id":"15","cell":["15","2018","Irvine","GUADALUPE","VALADEZ","MED CTR CUSTODIAN SR","34966.00","31341.00","2130.00","1495.00"]},
{"id":"16","cell":["16","2018","Davis","THERESE C","SCOTT","BLANK AST 2","34966.00","34966.00","0.00","0.00"]},
{"id":"17","cell":["17","2018","Santa Barbara","*****","*****","GSR-NO REM","34966.00","34966.00","0.00","0.00"]},
{"id":"18","cell":["18","2018","Berkeley","RANELL","HOLMES","TCHL PROJECT MGT PROFL 4","34965.00","34965.00","0.00","0.00"]},
{"id":"19","cell":["19","2018","Riverside","SAMUEL","LEBOWITZ","COACH AST 3","34965.00","34965.00","0.00","0.00"]},
{"id":"20","cell":["20","2018","Santa Barbara","*****","*****","GSR-TUIT & FEE REM","34964.00","34964.00","0.00","0.00"]}]
}
