{
"page" : "7260",
"total" : "15515",
"records" : "310295",
"rows":[
{"id":"1","cell":["1","2018","San Francisco","RIMMA","SANKIN","BLANK AST 2","34595.00","32604.00","355.00","1636.00"]},
{"id":"2","cell":["2","2018","Davis","*****","*****","GSR-FULL FEE REM","34595.00","26840.00","0.00","7755.00"]},
{"id":"3","cell":["3","2018","Santa Cruz","NADA","MILJKOVIC","LECT-AY-1/9","34595.00","26362.00","0.00","8233.00"]},
{"id":"4","cell":["4","2018","San Diego","*****","*****","ASSOC IN __ -AY-1/9-GSHIP","34595.00","31366.00","0.00","3229.00"]},
{"id":"5","cell":["5","2018","Irvine","KALEV","KASK","LECT-AY-1/9","34592.00","34592.00","0.00","0.00"]},
{"id":"6","cell":["6","2018","Davis","TONYA L","BYRUM","HOSP BLANK AST 3","34591.00","33241.00","239.00","1111.00"]},
{"id":"7","cell":["7","2018","Davis","TAMI R","SANDEEN","CMTY EDUC SPEC 2","34591.00","34591.00","0.00","0.00"]},
{"id":"8","cell":["8","2018","Riverside","LINDSEY","AGNEW","JR SPECIALIST","34591.00","34591.00","0.00","0.00"]},
{"id":"9","cell":["9","2018","Los Angeles","CHRISTIAN","PAREDES MADRID","PROGR ANL 3","34590.00","34590.00","0.00","0.00"]},
{"id":"10","cell":["10","2018","Los Angeles","JASON","LEE","FOOD SVC MGR AST SUPV","34589.00","29072.00","5257.00","260.00"]},
{"id":"11","cell":["11","2018","San Diego","JULIA","SCHRIBER","ULTRASOUND TCHNO SR PD","34589.00","32196.00","2254.00","139.00"]},
{"id":"12","cell":["12","2018","Davis","BETHANY F","WELLMAN","NON-PHYS CLIN TRAIN-GENL CAMP","34587.00","31312.00","0.00","3275.00"]},
{"id":"13","cell":["13","2018","Los Angeles","AMAR","ALVAREZ","PAT COMM REPR","34587.00","34201.00","386.00","0.00"]},
{"id":"14","cell":["14","2018","Irvine","GREGORY S","CARR","CLIN LAB SCI SPEC","34586.00","21265.00","402.00","12919.00"]},
{"id":"15","cell":["15","2018","Davis","KELLY L","KIM","SALES SPEC 2","34586.00","34026.00","0.00","560.00"]},
{"id":"16","cell":["16","2018","San Diego","JACQUES CHRISTOP","HARRIS","NURSE PD","34586.00","31128.00","588.00","2870.00"]},
{"id":"17","cell":["17","2018","Berkeley","YETEM","SANCHEZ","COOK","34585.00","30965.00","3450.00","170.00"]},
{"id":"18","cell":["18","2018","San Francisco","DAVID VIBULAN","ALLEGAKOEN","ASST SPECIALIST","34585.00","34585.00","0.00","0.00"]},
{"id":"19","cell":["19","2018","Berkeley","LOI AMEERA","ALMERON","ASST SPECIALIST","34585.00","34585.00","0.00","0.00"]},
{"id":"20","cell":["20","2018","Los Angeles","CINDY","MATA","PUBL ADMSTN ANL SR","34583.00","34583.00","0.00","0.00"]}]
}
