{
"page" : "873",
"total" : "15515",
"records" : "310295",
"rows":[
{"id":"1","cell":["1","2018","San Francisco","ANGEL A","CARLOS","CLIN NURSE 2","165438.00","151854.00","9282.00","4302.00"]},
{"id":"2","cell":["2","2018","Los Angeles","PREST","OSHODI","ADMIN NURSE 2 NEX","165435.00","156524.00","1070.00","7841.00"]},
{"id":"3","cell":["3","2018","San Diego","YUNDE","ZHAO","PROF-AY","165435.00","145925.00","0.00","19510.00"]},
{"id":"4","cell":["4","2018","Davis","THOMAS M","GRADZIEL","AGRON AES","165434.00","165234.00","0.00","200.00"]},
{"id":"5","cell":["5","2018","Berkeley","RICHARD","BLIGH","DATABASE ADM 5","165433.00","164183.00","0.00","1250.00"]},
{"id":"6","cell":["6","2018","Riverside","CATHY","ECKMAN","ADMIN MGR 3","165432.00","163432.00","0.00","2000.00"]},
{"id":"7","cell":["7","2018","UCOP","JONAS","LERMA","COMPENSATION ANL 5","165431.00","164931.00","0.00","500.00"]},
{"id":"8","cell":["8","2018","Davis","SUSAN L","JOHNSON","ACAD PRG MGT OFCR 3","165430.00","110266.00","0.00","55164.00"]},
{"id":"9","cell":["9","2018","Los Angeles","YACGLEY","VALDES","DIR","165427.00","99319.00","0.00","66108.00"]},
{"id":"10","cell":["10","2018","San Francisco","CHESTER L","LIM","RADLG SVC SUPV 2","165421.00","154731.00","3463.00","7227.00"]},
{"id":"11","cell":["11","2018","San Francisco","MARIA ELENA","RYAN","FINANCIAL ANL 4 GF","165417.00","147988.00","0.00","17429.00"]},
{"id":"12","cell":["12","2018","Los Angeles","GRACE HYUN","KIM","ASSOC PROF IN RES-HCOMP","165416.00","117749.00","0.00","47667.00"]},
{"id":"13","cell":["13","2018","Berkeley","ARASH","KOMEILI","AGRON AES-AY","165412.00","128842.00","0.00","36570.00"]},
{"id":"14","cell":["14","2018","Davis","NINNA S","ABILO","NURSE SVC SUPV 2","165408.00","147708.00","3907.00","13793.00"]},
{"id":"15","cell":["15","2018","Davis","DANIEL A","CEBRA","PROF-AY","165402.00","144238.00","0.00","21164.00"]},
{"id":"16","cell":["16","2018","San Francisco","TULA BELLE","VIAU","NURSE PD","165400.00","144714.00","5089.00","15597.00"]},
{"id":"17","cell":["17","2018","Los Angeles","SHERRY LYNN","CEDENO","ADMIN NURSE 1","165394.00","146371.00","2017.00","17006.00"]},
{"id":"18","cell":["18","2018","Davis","JULIA","SIMON","PROF-AY","165391.00","165391.00","0.00","0.00"]},
{"id":"19","cell":["19","2018","Los Angeles","SHARON","DOGGETT","ADMIN NURSE 2 NEX","165388.00","133919.00","21000.00","10469.00"]},
{"id":"20","cell":["20","2018","Los Angeles","JACK","TCHILINGIRIAN","COMPUTING RESC MGR 2","165385.00","163385.00","0.00","2000.00"]}]
}
