{
"page" : "2244",
"total" : "15515",
"records" : "310295",
"rows":[
{"id":"1","cell":["1","2018","Davis","MITCHELL S","MOBLEY","CLIN NURSE 2","105066.00","103378.00","1688.00","0.00"]},
{"id":"2","cell":["2","2018","Davis","JULIE W","BURGES","CLIN LAB MGR 1","105066.00","105066.00","0.00","0.00"]},
{"id":"3","cell":["3","2018","San Diego","NATALIE ELIZABET","FISHER","CLIN NURSE 2","105064.00","96890.00","3558.00","4616.00"]},
{"id":"4","cell":["4","2018","Los Angeles","THOMAS","TRUONG","CLIN LAB SCI","105062.00","96230.00","950.00","7882.00"]},
{"id":"5","cell":["5","2018","Los Angeles","TIFFANY","JOHNSON","CLIN NURSE 2","105061.00","101254.00","1528.00","2279.00"]},
{"id":"6","cell":["6","2018","Los Angeles","LEONID","KRUGLYAK","PROF-HCOMP","105060.00","0.00","0.00","105060.00"]},
{"id":"7","cell":["7","2018","Davis","DALJIT","KAUR","CLIN NURSE 2","105060.00","91035.00","3522.00","10503.00"]},
{"id":"8","cell":["8","2018","San Diego","YASSAR HUSSAIN","ARAIN","HS ASST CLIN PROF-HCOMP","105060.00","58825.00","0.00","46235.00"]},
{"id":"9","cell":["9","2018","Los Angeles","BLAKE","RAINY","ELECTRN LD","105058.00","87755.00","11565.00","5738.00"]},
{"id":"10","cell":["10","2018","San Francisco","VEENA IYER","SINGLA","ACADEMIC COORD III-FY","105057.00","105057.00","0.00","0.00"]},
{"id":"11","cell":["11","2018","Los Angeles","STUART","WOLPERT","ADMIN ANL PRN 1","105054.00","105054.00","0.00","0.00"]},
{"id":"12","cell":["12","2018","Davis","DEBORAH L","ROBINSON","CARDIOVASCULAR TCHN","105052.00","101526.00","3492.00","34.00"]},
{"id":"13","cell":["13","2018","San Diego","AURORA CASTILLO","PULIDO","CASE MGR EX","105051.00","104051.00","0.00","1000.00"]},
{"id":"14","cell":["14","2018","Davis","ROSEMARY","MARTIN-OCAMPO","ADMIN MGR 1","105049.00","105049.00","0.00","0.00"]},
{"id":"15","cell":["15","2018","Los Angeles","JULIUS EARL","GO","PROGR ANL 4","105049.00","100879.00","0.00","4170.00"]},
{"id":"16","cell":["16","2018","San Diego","KIMBERLY DAVIS","KING","LECT-AY-1/9","105047.00","50064.00","0.00","54983.00"]},
{"id":"17","cell":["17","2018","San Diego","JENNA MARIE","CURRY","CLIN NURSE 2","105046.00","93972.00","4412.00","6662.00"]},
{"id":"18","cell":["18","2018","Davis","ELIZON V","RAMOS","CLIN NURSE 2","105045.00","91533.00","2371.00","11141.00"]},
{"id":"19","cell":["19","2018","UCOP","ANNE","SCOTT","PAYROLL MGR 1","105045.00","104795.00","0.00","250.00"]},
{"id":"20","cell":["20","2018","Davis","DOROTHY K","CHAN","FINANCIAL ANL 4","105042.00","105042.00","0.00","0.00"]}]
}
