{
"page" : "2907",
"total" : "15515",
"records" : "310295",
"rows":[
{"id":"1","cell":["1","2018","Los Angeles","SURAN","THRIFT","ADMIN ANL PRN 1","88119.00","88119.00","0.00","0.00"]},
{"id":"2","cell":["2","2018","Davis","ROMANA A","NORTON","STDT LIFE DEV SPEC 4","88118.00","87821.00","0.00","297.00"]},
{"id":"3","cell":["3","2018","Berkeley","SHARAY","PINERO","FAC SUPV 1","88118.00","87618.00","0.00","500.00"]},
{"id":"4","cell":["4","2018","Los Angeles","GANG","LIU","ASSOC PROF-AY","88117.00","88117.00","0.00","0.00"]},
{"id":"5","cell":["5","2018","Davis","SCOTT S","KELLEY","DIGITAL COMM SUPV 2","88113.00","84868.00","0.00","3245.00"]},
{"id":"6","cell":["6","2018","Los Angeles","MAYA","KING","RESC NURSE PD","88113.00","86448.00","266.00","1399.00"]},
{"id":"7","cell":["7","2018","Los Angeles","PARTHA","SINHA","STEAM OPS ENGR","88112.00","81031.00","6516.00","565.00"]},
{"id":"8","cell":["8","2018","Los Angeles","KATHLEEN","AMANO","ADMIN ANL SR","88110.00","88110.00","0.00","0.00"]},
{"id":"9","cell":["9","2018","San Francisco","KATYA L","SALCEDO","CLIN RSCH ANL 4","88109.00","88109.00","0.00","0.00"]},
{"id":"10","cell":["10","2018","Davis","BRYAN T","MU","REG RESP THER 1","88109.00","85496.00","1794.00","819.00"]},
{"id":"11","cell":["11","2018","Santa Barbara","JOSE","CARRANZA","ZONE LD","88109.00","83464.00","4645.00","0.00"]},
{"id":"12","cell":["12","2018","Los Angeles","LUZ","ANAYA","DENTAL HYGIENIST","88109.00","86987.00","1122.00","0.00"]},
{"id":"13","cell":["13","2018","Santa Cruz","MADHAVI MOHAN","MURTY","ASST PROF-AY","88108.00","88108.00","0.00","0.00"]},
{"id":"14","cell":["14","2018","San Diego","J HAL","ROMANS","RSCH AND DEV ENGR 4","88108.00","88108.00","0.00","0.00"]},
{"id":"15","cell":["15","2018","Berkeley","JEFFREY","WOODS","STDT LIFE DEV SPEC 4","88104.00","88104.00","0.00","0.00"]},
{"id":"16","cell":["16","2018","Berkeley","SHIRLEYRAE","REED","ADMIN OFCR 3","88102.00","88102.00","0.00","0.00"]},
{"id":"17","cell":["17","2018","Berkeley","KERRY","HAYS","BUS SYS ANL 3","88100.00","88100.00","0.00","0.00"]},
{"id":"18","cell":["18","2018","Irvine","JESSE A","NAVA","CLIN NURSE 2","88098.00","77218.00","8098.00","2782.00"]},
{"id":"19","cell":["19","2018","San Francisco","BORDEN M","WONG","HOSP UNIT SVC CRD 3","88095.00","65327.00","13320.00","9448.00"]},
{"id":"20","cell":["20","2018","Los Angeles","ISMAIL","MITCHELL","PROGR ANL 5 SUPV","88095.00","88095.00","0.00","0.00"]}]
}
