{
"page" : "4195",
"total" : "15515",
"records" : "310295",
"rows":[
{"id":"1","cell":["1","2018","Davis","REINA S.","DELA CRUZ","BUS TCHL SUPP ANL 3","65796.00","65796.00","0.00","0.00"]},
{"id":"2","cell":["2","2018","Irvine","LINDA GEORGIA","MUNOZ","COLL REPR SR SUPV","65795.00","65795.00","0.00","0.00"]},
{"id":"3","cell":["3","2018","San Diego","STEPHANIE CHAVEZ","MARTINEZ","NURSE PD","65795.00","63065.00","2624.00","106.00"]},
{"id":"4","cell":["4","2018","San Francisco","ELAINE S","SAMPIOR","RSCH ADM 3","65793.00","48702.00","0.00","17091.00"]},
{"id":"5","cell":["5","2018","Berkeley","ANGELA","DIZON","PAYROLL ANL 2","65793.00","63774.00","2019.00","0.00"]},
{"id":"6","cell":["6","2018","San Diego","BECKY SUE","COULTER","NURSE PD","65792.00","36120.00","13146.00","16526.00"]},
{"id":"7","cell":["7","2018","Los Angeles","RASHID","AHMED","CLIN CARE PARTNER","65791.00","52386.00","5935.00","7470.00"]},
{"id":"8","cell":["8","2018","San Francisco","LEONEL ALBERTO","NAJERA","BLDG MAINT WORKER SR","65790.00","65509.00","281.00","0.00"]},
{"id":"9","cell":["9","2018","San Diego","EDWARD HANS","KEENAN","BOATSWAIN 3","65790.00","62825.00","2965.00","0.00"]},
{"id":"10","cell":["10","2018","Los Angeles","STEPHANIE","NAKAI","PRG PROMOTION MGR 1","65788.00","65788.00","0.00","0.00"]},
{"id":"11","cell":["11","2018","Los Angeles","JUSTIN","YEH","ACCOUNTANT 1","65788.00","65788.00","0.00","0.00"]},
{"id":"12","cell":["12","2018","San Francisco","NATALIYA","RUSSIYANOVA","GI ENDOSCOPY TCHN 1","65787.00","63974.00","787.00","1026.00"]},
{"id":"13","cell":["13","2018","Davis","NAZRA","BIBI","PHLEBOTOMIST CERT TCHN 2","65787.00","65332.00","87.00","368.00"]},
{"id":"14","cell":["14","2018","Los Angeles","RAFAEL","CABRERA","PARKING SUPV SR","65786.00","58971.00","5303.00","1512.00"]},
{"id":"15","cell":["15","2018","Irvine","ARMANDO U.","ARIAS","BLDG MAINT WORKER LD","65784.00","57504.00","3239.00","5041.00"]},
{"id":"16","cell":["16","2018","Los Angeles","CRISTINA","REYES","BLANK AST 3","65784.00","63960.00","824.00","1000.00"]},
{"id":"17","cell":["17","2018","San Diego","DOUG","LANE","PAINTER","65784.00","65784.00","0.00","0.00"]},
{"id":"18","cell":["18","2018","Berkeley","ALEXANDER","REYES","EMPLOYMENT REPR 2","65784.00","59789.00","824.00","5171.00"]},
{"id":"19","cell":["19","2018","Los Angeles","KURT","SCHWETER","FOOD SVC MGR SR","65783.00","66383.00","0.00","-600.00"]},
{"id":"20","cell":["20","2018","Davis","JULIE A.","FINZEL","ASST COOP EXT ADVISOR","65783.00","65783.00","0.00","0.00"]}]
}
