{
"page" : "8834",
"total" : "15515",
"records" : "310295",
"rows":[
{"id":"1","cell":["1","2018","Irvine","*****","*****","GSR-FULL FEE REM","18820.00","18820.00","0.00","0.00"]},
{"id":"2","cell":["2","2018","Los Angeles","*****","*****","LAB AST 1","18820.00","18820.00","0.00","0.00"]},
{"id":"3","cell":["3","2018","Los Angeles","*****","*****","STDT 4","18818.00","17245.00","1197.00","376.00"]},
{"id":"4","cell":["4","2018","Davis","*****","*****","TEACHG ASST-GSHIP","18818.00","18360.00","0.00","458.00"]},
{"id":"5","cell":["5","2018","Riverside","DANIKA","GLOVER","PHLEBOTOMIST CERT 1","18818.00","17798.00","2.00","1018.00"]},
{"id":"6","cell":["6","2018","San Francisco","MINHTHU THI","LE","BLANK AST 3","18817.00","18817.00","0.00","0.00"]},
{"id":"7","cell":["7","2018","Irvine","*****","*****","TEACHG ASST-GSHIP","18816.00","16116.00","0.00","2700.00"]},
{"id":"8","cell":["8","2018","Davis","*****","*****","GSR-FULL FEE REM","18816.00","18816.00","0.00","0.00"]},
{"id":"9","cell":["9","2018","Riverside","CARLA","URMENETA","FINANCIAL ANL 1","18816.00","18816.00","0.00","0.00"]},
{"id":"10","cell":["10","2018","Riverside","DESTINY","BRITTON","FINANCIAL ANL 1","18816.00","18816.00","0.00","0.00"]},
{"id":"11","cell":["11","2018","Los Angeles","AMAURI","CHAVEZ","ADMIN ANL AST","18815.00","18365.00","0.00","450.00"]},
{"id":"12","cell":["12","2018","Santa Barbara","*****","*****","REMD TUT II-NON GSHIP","18814.00","18714.00","0.00","100.00"]},
{"id":"13","cell":["13","2018","San Diego","JOSE P","HERNANDEZ","FOOD SVC WORKER","18813.00","17337.00","1276.00","200.00"]},
{"id":"14","cell":["14","2018","Berkeley","*****","*****","TEACHG ASST-GSHIP","18811.00","18711.00","0.00","100.00"]},
{"id":"15","cell":["15","2018","Berkeley","*****","*****","TEACHG ASST-GSHIP","18811.00","18711.00","0.00","100.00"]},
{"id":"16","cell":["16","2018","Berkeley","*****","*****","TEACHG ASST-GSHIP","18811.00","18711.00","0.00","100.00"]},
{"id":"17","cell":["17","2018","Berkeley","*****","*****","TEACHG ASST-GSHIP","18811.00","18711.00","0.00","100.00"]},
{"id":"18","cell":["18","2018","Berkeley","*****","*****","TEACHG ASST-GSHIP","18811.00","18711.00","0.00","100.00"]},
{"id":"19","cell":["19","2018","Berkeley","*****","*****","TEACHG ASST-GSHIP","18811.00","18711.00","0.00","100.00"]},
{"id":"20","cell":["20","2018","Berkeley","*****","*****","TEACHG ASST-GSHIP","18811.00","18711.00","0.00","100.00"]}]
}
